is3_python_kafka/__init__.py
is3_python_kafka/custom/__init__.py
is3_python_kafka/custom/execute.py
is3_python_kafka/data_query/__init__.py
is3_python_kafka/data_query/meta_data.py
is3_python_kafka/domain/__init__.py
is3_python_kafka/domain/data_dto.py
is3_python_kafka/is3_config/__init__.py
is3_python_kafka/is3_config/is3_sys_config.ini
is3_python_kafka/is3_kafka/__init__.py
is3_python_kafka/is3_kafka/kafka_execute.py
is3_python_kafka/nacos_server/__init__.py
is3_python_kafka/nacos_server/nacos_server.py
is3_python_kafka/utils/__init__.py
is3_python_kafka/utils/create_app.py
is3_python_kafka/utils/header_util.py
is3_python_kafka/utils/is3_request_util.py
is3_python_kafka/utils/kafka_component_util.py
is3_python_kafka/utils/load_config.py
is3_python_kafka/utils/logger.py
is3_python_kafka/utils/plugin_log_util.py
is3_python_kafka-4.0.dist-info/LICENSE
is3_python_kafka-4.0.dist-info/METADATA
is3_python_kafka-4.0.dist-info/WHEEL
is3_python_kafka-4.0.dist-info/entry_points.txt
is3_python_kafka-4.0.dist-info/top_level.txt
is3_python_kafka-4.0.dist-info/RECORD
